Counter.v
module counter(Q, clock, clear);
output reg [3:0]Q;
input clock, clear;

always @(posedge clear or negedge clock)
begin
    if(clear)
    Q<=0;
    else
    Q <= (Q+1)%16;
end
endmodule

Counter/CounterTB.v
module CounterTB;
    wire [3:0] Q;
    reg clock, clear;

    counter c1(Q, clock, clear);

    initial begin

    $dumpfile("CounterTB.vcd");  // Specify dump file name

    $dumpvars(0, CounterTB);  // Dump all signals in the testbench

    end

    initial begin
    clock = 0;
    forever #5 clock = ~clock;
    end

    initial begin
    // Initialize
    clear = 1;
    #10;

    // Release clear
    clear = 0;
    
    // Run for several clock cycles
    #100;

    // Assert clear again
    clear = 1;
    #10;
    clear = 0;

    // Run again
    #50;

    // Finish simulation
    #1000 $finish;
  end
    initial begin
    $display($time, "value of clear=%b, Q=%b", clear, Q);
    end
endmodule

Counter/CounterTB.vcd
$date
	Sat Apr 26 09:33:58 2025
$end
$version
	Icarus Verilog
$end
$timescale
	1s
$end
$scope module CounterTB $end
$var wire 4 ! Q [3:0] $end
$var reg 1 " clear $end
$var reg 1 # clock $end
$scope module c1 $end
$var wire 1 " clear $end
$var wire 1 # clock $end
$var reg 4 $ Q [3:0] $end
$upscope $end
$upscope $end
$enddefinitions $end
$comment Show the parameter values. $end
$dumpall
$end
#0
$dumpvars
b0 $
0#
1"
b0 !
$end
#5
1#
#10
b1 !
b1 $
0#
0"
#15
1#
#20
b10 !
b10 $
0#
#25
1#
#30
b11 !
b11 $
0#
#35
1#
#40
b100 !
b100 $
0#
#45
1#
#50
b101 !
b101 $
0#
#55
1#
#60
b110 !
b110 $
0#
#65
1#
#70
b111 !
b111 $
0#
#75
1#
#80
b1000 !
b1000 $
0#
#85
1#
#90
b1001 !
b1001 $
0#
#95
1#
#100
b1010 !
b1010 $
0#
#105
1#
#110
b0 !
b0 $
0#
1"
#115
1#
#120
b1 !
b1 $
0#
0"
#125
1#
#130
b10 !
b10 $
0#
#135
1#
#140
b11 !
b11 $
0#
#145
1#
#150
b100 !
b100 $
0#
#155
1#
#160
b101 !
b101 $
0#
#165
1#
#170
b110 !
b110 $
0#
#175
1#
#180
b111 !
b111 $
0#
#185
1#
#190
b1000 !
b1000 $
0#
#195
1#
#200
b1001 !
b1001 $
0#
#205
1#
#210
b1010 !
b1010 $
0#
#215
1#
#220
b1011 !
b1011 $
0#
#225
1#
#230
b1100 !
b1100 $
0#
#235
1#
#240
b1101 !
b1101 $
0#
#245
1#
#250
b1110 !
b1110 $
0#
#255
1#
#260
b1111 !
b1111 $
0#
#265
1#
#270
b0 !
b0 $
0#
#275
1#
#280
b1 !
b1 $
0#
#285
1#
#290
b10 !
b10 $
0#
#295
1#
#300
b11 !
b11 $
0#
#305
1#
#310
b100 !
b100 $
0#
#315
1#
#320
b101 !
b101 $
0#
#325
1#
#330
b110 !
b110 $
0#
#335
1#
#340
b111 !
b111 $
0#
#345
1#
#350
b1000 !
b1000 $
0#
#355
1#
#360
b1001 !
b1001 $
0#
#365
1#
#370
b1010 !
b1010 $
0#
#375
1#
#380
b1011 !
b1011 $
0#
#385
1#
#390
b1100 !
b1100 $
0#
#395
1#
#400
b1101 !
b1101 $
0#
#405
1#
#410
b1110 !
b1110 $
0#
#415
1#
#420
b1111 !
b1111 $
0#
#425
1#
#430
b0 !
b0 $
0#
#435
1#
#440
b1 !
b1 $
0#
#445
1#
#450
b10 !
b10 $
0#
#455
1#
#460
b11 !
b11 $
0#
#465
1#
#470
b100 !
b100 $
0#
#475
1#
#480
b101 !
b101 $
0#
#485
1#
#490
b110 !
b110 $
0#
#495
1#
#500
b111 !
b111 $
0#
#505
1#
#510
b1000 !
b1000 $
0#
#515
1#
#520
b1001 !
b1001 $
0#
#525
1#
#530
b1010 !
b1010 $
0#
#535
1#
#540
b1011 !
b1011 $
0#
#545
1#
#550
b1100 !
b1100 $
0#
#555
1#
#560
b1101 !
b1101 $
0#
#565
1#
#570
b1110 !
b1110 $
0#
#575
1#
#580
b1111 !
b1111 $
0#
#585
1#
#590
b0 !
b0 $
0#
#595
1#
#600
b1 !
b1 $
0#
#605
1#
#610
b10 !
b10 $
0#
#615
1#
#620
b11 !
b11 $
0#
#625
1#
#630
b100 !
b100 $
0#
#635
1#
#640
b101 !
b101 $
0#
#645
1#
#650
b110 !
b110 $
0#
#655
1#
#660
b111 !
b111 $
0#
#665
1#
#670
b1000 !
b1000 $
0#
#675
1#
#680
b1001 !
b1001 $
0#
#685
1#
#690
b1010 !
b1010 $
0#
#695
1#
#700
b1011 !
b1011 $
0#
#705
1#
#710
b1100 !
b1100 $
0#
#715
1#
#720
b1101 !
b1101 $
0#
#725
1#
#730
b1110 !
b1110 $
0#
#735
1#
#740
b1111 !
b1111 $
0#
#745
1#
#750
b0 !
b0 $
0#
#755
1#
#760
b1 !
b1 $
0#
#765
1#
#770
b10 !
b10 $
0#
#775
1#
#780
b11 !
b11 $
0#
#785
1#
#790
b100 !
b100 $
0#
#795
1#
#800
b101 !
b101 $
0#
#805
1#
#810
b110 !
b110 $
0#
#815
1#
#820
b111 !
b111 $
0#
#825
1#
#830
b1000 !
b1000 $
0#
#835
1#
#840
b1001 !
b1001 $
0#
#845
1#
#850
b1010 !
b1010 $
0#
#855
1#
#860
b1011 !
b1011 $
0#
#865
1#
#870
b1100 !
b1100 $
0#
#875
1#
#880
b1101 !
b1101 $
0#
#885
1#
#890
b1110 !
b1110 $
0#
#895
1#
#900
b1111 !
b1111 $
0#
#905
1#
#910
b0 !
b0 $
0#
#915
1#
#920
b1 !
b1 $
0#
#925
1#
#930
b10 !
b10 $
0#
#935
1#
#940
b11 !
b11 $
0#
#945
1#
#950
b100 !
b100 $
0#
#955
1#
#960
b101 !
b101 $
0#
#965
1#
#970
b110 !
b110 $
0#
#975
1#
#980
b111 !
b111 $
0#
#985
1#
#990
b1000 !
b1000 $
0#
#995
1#
#1000
b1001 !
b1001 $
0#
#1005
1#
#1010
b1010 !
b1010 $
0#
#1015
1#
#1020
b1011 !
b1011 $
0#
#1025
1#
#1030
b1100 !
b1100 $
0#
#1035
1#
#1040
b1101 !
b1101 $
0#
#1045
1#
#1050
b1110 !
b1110 $
0#
#1055
1#
#1060
b1111 !
b1111 $
0#
#1065
1#
#1070
b0 !
b0 $
0#
#1075
1#
#1080
b1 !
b1 $
0#
#1085
1#
#1090
b10 !
b10 $
0#
#1095
1#
#1100
b11 !
b11 $
0#
#1105
1#
#1110
b100 !
b100 $
0#
#1115
1#
#1120
b101 !
b101 $
0#
#1125
1#
#1130
b110 !
b110 $
0#
#1135
1#
#1140
b111 !
b111 $
0#
#1145
1#
#1150
b1000 !
b1000 $
0#
#1155
1#
#1160
b1001 !
b1001 $
0#
#1165
1#
#1170
b1010 !
b1010 $
0#
